{"cameraMode":{"drawMode":0,"name":"Shaded","section":"Shading Mode"},"sceneLighting":true,"audioPlay":false,"sceneViewState":{"showFog":true,"showMaterialUpdate":false,"showSkybox":true,"showFlares":true,"showImageEffects":true,"showParticleSystems":true},"in2DMode":false,"pivot":{"x":1010.9615478515625,"y":578.3060302734375,"z":113.6964111328125},"rotation":{"x":0.00599990040063858,"y":-0.003000110387802124,"z":0.0000179775342985522,"w":0.9999769330024719},"size":585.7929077148438,"orthographic":false}